showml/__init__.py
showml/deep_learning/__init__.py
showml/deep_learning/activations.py
showml/deep_learning/base_layer.py
showml/deep_learning/layers.py
showml/deep_learning/model.py
showml/linear_model/__init__.py
showml/linear_model/regression.py
showml/losses/__init__.py
showml/losses/base_loss.py
showml/losses/loss_functions.py
showml/losses/metrics.py
showml/optimizers/__init__.py
showml/optimizers/base_optimizer.py
showml/optimizers/optimizer_functions.py
showml/utils/__init__.py
showml/utils/data_loader.py
showml/utils/dataset.py
showml/utils/exceptions.py
showml/utils/model_utilities.py
showml/utils/plots.py
showml/utils/preprocessing.py
tests/__init__.py
tests/losses/__init__.py
tests/losses/test_loss_functions.py
tests/losses/test_metrics.py
tests/optimizers/__init__.py
tests/optimizers/test_optimizers.py
tests/utils/__init__.py
tests/utils/test_dataset.py
tests/utils/test_preprocessing.py
showml-1.6.12.dist-info/LICENSE
showml-1.6.12.dist-info/METADATA
showml-1.6.12.dist-info/WHEEL
showml-1.6.12.dist-info/top_level.txt
showml-1.6.12.dist-info/RECORD
