Metadata-Version: 2.1
Name: showml
Version: 1.6.12
Summary: A Python package of Machine Learning Algorithms implemented from scratch
Home-page: https://github.com/hasnainroopawalla/ShowML
Author: Hasnain Roopawalla
Author-email: hasnain.roopawalla@gmail.com
License: MIT
Keywords: python,machinelearning,ai
Platform: UNKNOWN
Classifier: License :: OSI Approved :: MIT License
Classifier: Intended Audience :: Developers
Classifier: Topic :: Scientific/Engineering :: Artificial Intelligence
Classifier: Operating System :: OS Independent
Classifier: Programming Language :: Python :: 3 :: Only
Classifier: Programming Language :: Python :: 3.6
Classifier: Programming Language :: Python :: 3.7
Classifier: Programming Language :: Python :: 3.8
Classifier: Programming Language :: Python :: 3.9
Requires-Python: >=3.6
